pillow_snippet/__init__.py
pillow_snippet/convert.py
pillow_snippet/mask.py
pillow_snippet-0.0.4.dist-info/LICENSE
pillow_snippet-0.0.4.dist-info/METADATA
pillow_snippet-0.0.4.dist-info/WHEEL
pillow_snippet-0.0.4.dist-info/top_level.txt
pillow_snippet-0.0.4.dist-info/RECORD
