Metadata-Version: 2.1
Name: pillow-snippet
Version: 0.0.4
Summary: some useful snippet for image
Home-page: https://github.com/ramwin/pillow_snippet
Author: Xiang Wang
Author-email: ramwin@qq.com
License: UNKNOWN
Platform: UNKNOWN
Classifier: Programming Language :: Python :: 3
Classifier: License :: OSI Approved :: MIT License
Classifier: Operating System :: OS Independent
